AUTHORS
HISTORY
LICENSE
LICENSES
MANIFEST.in
README.rst
setup.py
django_filero.egg-info/PKG-INFO
django_filero.egg-info/SOURCES.txt
django_filero.egg-info/dependency_links.txt
django_filero.egg-info/not-zip-safe
django_filero.egg-info/requires.txt
django_filero.egg-info/top_level.txt
filer/__init__.py
filer/apps.py
filer/settings.py
filer/storage.py
filer/thumbnail_processors.py
filer/views.py
filer/admin/__init__.py
filer/admin/clipboardadmin.py
filer/admin/fileadmin.py
filer/admin/folderadmin.py
filer/admin/forms.py
filer/admin/imageadmin.py
filer/admin/permissionadmin.py
filer/admin/permissions.py
filer/admin/tools.py
filer/admin/patched/__init__.py
filer/admin/patched/admin_utils.py
filer/fields/__init__.py
filer/fields/file.py
filer/fields/folder.py
filer/fields/image.py
filer/fields/multistorage_file.py
filer/locale/.DS_Store
filer/locale/README
filer/locale/ca/.DS_Store
filer/locale/ca/LC_MESSAGES/django.mo
filer/locale/ca/LC_MESSAGES/django.po
filer/locale/de/LC_MESSAGES/django.mo
filer/locale/de/LC_MESSAGES/django.po
filer/locale/en/.DS_Store
filer/locale/en/LC_MESSAGES/django.mo
filer/locale/en/LC_MESSAGES/django.po
filer/locale/es/.DS_Store
filer/locale/es/LC_MESSAGES/django.mo
filer/locale/es/LC_MESSAGES/django.po
filer/locale/et/LC_MESSAGES/django.mo
filer/locale/et/LC_MESSAGES/django.po
filer/locale/eu/LC_MESSAGES/django.mo
filer/locale/eu/LC_MESSAGES/django.po
filer/locale/fi/LC_MESSAGES/django.mo
filer/locale/fi/LC_MESSAGES/django.po
filer/locale/fr/LC_MESSAGES/django.mo
filer/locale/fr/LC_MESSAGES/django.po
filer/locale/gl/.DS_Store
filer/locale/gl/LC_MESSAGES/django.mo
filer/locale/gl/LC_MESSAGES/django.po
filer/locale/he/LC_MESSAGES/django.mo
filer/locale/he/LC_MESSAGES/django.po
filer/locale/hr/LC_MESSAGES/django.mo
filer/locale/hr/LC_MESSAGES/django.po
filer/locale/it/LC_MESSAGES/django.mo
filer/locale/it/LC_MESSAGES/django.po
filer/locale/lt/LC_MESSAGES/django.mo
filer/locale/lt/LC_MESSAGES/django.po
filer/locale/nb/LC_MESSAGES/django.mo
filer/locale/nb/LC_MESSAGES/django.po
filer/locale/nl_NL/LC_MESSAGES/django.mo
filer/locale/nl_NL/LC_MESSAGES/django.po
filer/locale/nn/LC_MESSAGES/django.mo
filer/locale/nn/LC_MESSAGES/django.po
