Metadata-Version: 1.1
Name: django-filero
Version: 0.2.4
Summary: A file management application for django that makes handling of files and images a breeze.
Home-page: https://github.com/oubiga/django-filero
Author: Stefan Foulis
Author-email: stefan@foulis.ch
License: BSD
Platform: OS Independent
Classifier: Development Status :: 4 - Beta
Classifier: Framework :: Django
Classifier: Intended Audience :: Developers
Classifier: License :: OSI Approved :: BSD License
Classifier: Operating System :: OS Independent
Classifier: Programming Language :: Python
Classifier: Topic :: Internet :: WWW/HTTP
Classifier: Programming Language :: Python :: 2.6
Classifier: Programming Language :: Python :: 2.7
Classifier: Programming Language :: Python :: 3.3
Classifier: Programming Language :: Python :: 3.4
